biobb_disc4alldata/__init__.py
biobb_disc4alldata/disc4alldata/__init__.py
biobb_disc4alldata/disc4alldata/common.py
biobb_disc4alldata/disc4alldata/convert_output.py
biobb_disc4alldata/disc4alldata/da_disgenet.py
biobb_disc4alldata/disc4alldata/dda_disgenet.py
biobb_disc4alldata/disc4alldata/ga_disgenet.py
biobb_disc4alldata/disc4alldata/gda_disgenet.py
biobb_disc4alldata/disc4alldata/hippie.py
biobb_disc4alldata/disc4alldata/template_container.py
biobb_disc4alldata/disc4alldata/va_disgenet.py
biobb_disc4alldata/disc4alldata/vda_disgenet.py
biobb_disc4alldata/test/__init__.py
biobb_disgenet/__init__.py
biobb_disgenet/disgenet/__init__.py
biobb_disgenet/disgenet/ass_disgenet.py
biobb_disgenet/disgenet/common.py
biobb_disgenet/disgenet/convert_output.py
biobb_disgenet/disgenet/da_disgenet.py
biobb_disgenet/disgenet/dda_disgenet.py
biobb_disgenet/disgenet/dga_disgenet.py
biobb_disgenet/disgenet/ga_disgenet.py
biobb_disgenet/disgenet/gda_disgenet.py
biobb_disgenet/disgenet/hippie.py
biobb_disgenet/disgenet/prova.py
biobb_disgenet/disgenet/prova_dda.py
biobb_disgenet/disgenet/prova_ga.py
biobb_disgenet/disgenet/prova_gda.py
biobb_disgenet/disgenet/template_container.py
biobb_disgenet/disgenet/uniprot_disgenet.py
biobb_disgenet/disgenet/va_disgenet.py
biobb_disgenet/disgenet/vda_disgenet.py
biobb_disgenet/test/__init__.py
biobb_disc4alldata-0.0.12.dist-info/LICENSE
biobb_disc4alldata-0.0.12.dist-info/METADATA
biobb_disc4alldata-0.0.12.dist-info/WHEEL
biobb_disc4alldata-0.0.12.dist-info/top_level.txt
biobb_disc4alldata-0.0.12.dist-info/RECORD
