Metadata-Version: 2.1
Name: biobb-disc4alldata
Version: 0.0.12
Summary: Biobb_disc4alldata is a complete code wrapper to interrogate the Disc4All pre-process database REST API.
Home-page: https://github.com/mapoferri/Biobb_disgenet
Author: Biobb developers - Maria Paola Ferri
Author-email: maria.ferri@bsc.es
License: UNKNOWN
Project-URL: Documentation, http://biobb_template.readthedocs.io/en/latest/
Project-URL: Bioexcel, https://bioexcel.eu/
Keywords: Bioinformatics Workflows BioExcel Compatibility
Platform: UNKNOWN
Classifier: Development Status :: 3 - Alpha
Classifier: Programming Language :: Python :: 3.7
Classifier: License :: OSI Approved :: Apache Software License
Classifier: Operating System :: MacOS :: MacOS X
Classifier: Operating System :: POSIX
Requires-Python: ==3.7.*
License-File: LICENSE
Requires-Dist: biobb-common (>=3.5.1)
